<?xml version="1.0" encoding="utf-8"?>
<SoundBanksInfo Platform="Mac" BasePlatform="Mac" SchemaVersion="16" SoundBankVersion="150">
	<RootPaths>
		<ProjectRoot>../..</ProjectRoot>
		<SourceFilesRoot>../../.cache/Mac</SourceFilesRoot>
		<SoundBanksRoot>.</SoundBanksRoot>
		<ExternalSourcesInputFile></ExternalSourcesInputFile>
		<ExternalSourcesOutputRoot>../../GeneratedSoundBanks/Mac</ExternalSourcesOutputRoot>
	</RootPaths>
	<DialogueEvents/>
	<SoundBanks>
		<SoundBank Id="1355168291" Type="User" Language="SFX" Hash="{272DB10E-DE5F-BC64-B948-9EBD76DA6246}">
			<ShortName>Init</ShortName>
			<Path>Init.bnk</Path>
			<Plugins>
				<Custom>
					<Plugin Id="134123109" Name="Gain (Custom)" LibName="Wwise Gain" LibId="9109507"/>
					<Plugin Id="322348316" Name="Meter (Custom)" LibName="Wwise Meter" LibId="8454147"/>
					<Plugin Id="470699092" Name="Meter (Custom)" LibName="Wwise Meter" LibId="8454147"/>
					<Plugin Id="498184372" Name="Gain (Custom)" LibName="Wwise Gain" LibId="9109507"/>
					<Plugin Id="562758421" Name="Meter (Custom)" LibName="Wwise Meter" LibId="8454147"/>
					<Plugin Id="610181853" Name="Meter (Custom)" LibName="Wwise Meter" LibId="8454147"/>
					<Plugin Id="777683974" Name="Gain (Custom)" LibName="Wwise Gain" LibId="9109507"/>
				</Custom>
				<ShareSets>
					<Plugin Id="1008402193" Name="Low_Pass_20KHz" LibName="Wwise Parametric EQ" LibId="6881283"/>
					<Plugin Id="3604890626" Name="High_Pass_60Hz" LibName="Wwise Parametric EQ" LibId="6881283"/>
				</ShareSets>
				<AudioDevices>
					<Plugin Id="2317455096" Name="No_Output" LibName="No Output" LibId="11862023"/>
					<Plugin Id="3859886410" Name="System" LibName="System" LibId="11403271"/>
				</AudioDevices>
			</Plugins>
			<Busses>
				<Bus Id="221867874" Name="EnvironmentBus"/>
				<Bus Id="309504875" Name="DialogueBus"/>
				<Bus Id="1966988073" Name="testBus">
					<PluginRefs>
						<Custom>
							<PluginRef Id="470699092"/>
						</Custom>
					</PluginRefs>
					<AuxBusRefs>
						<AuxBusRef Id="221139265" Name="auxHigh"/>
						<AuxBusRef Id="411780261" Name="auxLow"/>
						<AuxBusRef Id="1049182825" Name="auxMid"/>
					</AuxBusRefs>
				</Bus>
				<Bus Id="2886307548" Name="MusicBus"/>
				<Bus Id="3427258114" Name="SoundFXBus"/>
				<Bus Id="3803692087" Name="Master Audio Bus"/>
			</Busses>
			<AuxBusses>
				<AuxBus Id="221139265" Name="auxHigh">
					<PluginRefs>
						<Custom>
							<PluginRef Id="322348316"/>
							<PluginRef Id="498184372"/>
						</Custom>
						<ShareSets>
							<PluginRef Id="3604890626"/>
						</ShareSets>
					</PluginRefs>
				</AuxBus>
				<AuxBus Id="411780261" Name="auxLow">
					<PluginRefs>
						<Custom>
							<PluginRef Id="562758421"/>
							<PluginRef Id="777683974"/>
						</Custom>
						<ShareSets>
							<PluginRef Id="1008402193"/>
						</ShareSets>
					</PluginRefs>
				</AuxBus>
				<AuxBus Id="1049182825" Name="auxMid">
					<PluginRefs>
						<Custom>
							<PluginRef Id="134123109"/>
							<PluginRef Id="610181853"/>
						</Custom>
						<ShareSets>
							<PluginRef Id="1008402193"/>
							<PluginRef Id="3604890626"/>
						</ShareSets>
					</PluginRefs>
				</AuxBus>
			</AuxBusses>
			<GameParameters>
				<GameParameter Id="545371365" Name="Low"/>
				<GameParameter Id="1117531621" Name="Amp"/>
				<GameParameter Id="1182670505" Name="Mid"/>
				<GameParameter Id="2918011349" Name="MasterVolume"/>
				<GameParameter Id="3550808449" Name="High"/>
			</GameParameters>
			<StateGroups>
				<StateGroup Id="1021618141" Name="MusicState">
					<States>
						<State Id="89505537" Name="Gameplay"/>
						<State Id="748895195" Name="None"/>
					</States>
				</StateGroup>
				<StateGroup Id="2352559104" Name="CrowdSurfing">
					<States>
						<State Id="748895195" Name="None"/>
						<State Id="2260458779" Name="InCrowdSurf"/>
						<State Id="2475500331" Name="OutOfCrowdSurf"/>
					</States>
				</StateGroup>
			</StateGroups>
		</SoundBank>
		<SoundBank Id="3161908922" Type="User" Language="SFX" Hash="{FB6A902E-015E-F08A-2A04-74FA95F27E02}">
			<ShortName>Main</ShortName>
			<Path>Main.bnk</Path>
			<Media>
				<File Id="3886522" Language="SFX" Streaming="false" Location="Memory">
					<ShortName>Objects, Misc, Paint, Spray Can, Marble, Shake SND30684.wav</ShortName>
					<CachePath>SFX/Objects, Misc, Paint, Spray Can, Marble, Shake SND30684_94083B4A.wem</CachePath>
				</File>
				<File Id="5318352" Language="SFX" Streaming="false" Location="Memory">
					<ShortName>Zap2.wav</ShortName>
					<CachePath>SFX/Zap2_818F3B66.wem</CachePath>
				</File>
				<File Id="8926796" Language="SFX" Streaming="false" Location="Memory">
					<ShortName>Farts, Designed, Human Fart 07 SND88353.wav</ShortName>
					<CachePath>SFX/Farts, Designed, Human Fart 07 SND88353_818F3B66.wem</CachePath>
				</File>
				<File Id="20835932" Language="SFX" Streaming="false" Location="Memory">
					<ShortName>LotsOfSmallScratch.wav</ShortName>
					<CachePath>SFX/LotsOfSmallScratch_4A78A5E8.wem</CachePath>
				</File>
				<File Id="21833884" Language="SFX" Streaming="false" Location="Memory">
					<ShortName>Objects, Misc, Spray Paint, Painting, Aerosol SND70613.wav</ShortName>
					<CachePath>SFX/Objects, Misc, Spray Paint, Painting, Aerosol SND70613_C5716EAD.wem</CachePath>
				</File>
				<File Id="28928322" Language="SFX" Streaming="false" Location="Memory">
					<ShortName>Kick3.wav</ShortName>
					<CachePath>SFX/Kick3_818F3B66.wem</CachePath>
				</File>
				<File Id="42034528" Language="SFX" Streaming="false" Location="Memory">
					<ShortName>Objects, Misc, Spray Paint, Painting, Aerosol SND70613.wav</ShortName>
					<CachePath>SFX/Objects, Misc, Spray Paint, Painting, Aerosol SND70613_D6DC0D05.wem</CachePath>
				</File>
				<File Id="43950693" Language="SFX" Streaming="false" Location="Memory">
					<ShortName>Swoosh2.wav</ShortName>
					<CachePath>SFX/Swoosh2_818F3B66.wem</CachePath>
				</File>
				<File Id="55840581" Language="SFX" Streaming="false" Location="Memory">
					<ShortName>MicTap2.wav</ShortName>
					<CachePath>SFX/MicTap2_818F3B66.wem</CachePath>
				</File>
				<File Id="59239616" Language="SFX" Streaming="false" Location="Memory">
					<ShortName>MicTap1.wav</ShortName>
					<CachePath>SFX/MicTap1_818F3B66.wem</CachePath>
				</File>
				<File Id="64644625" Language="SFX" Streaming="false" Location="Memory">
					<ShortName>RockPlatformPush1.wav</ShortName>
					<CachePath>SFX/RockPlatformPush1_5559772D.wem</CachePath>
				</File>
				<File Id="73496553" Language="SFX" Streaming="false" Location="Memory">
					<ShortName>Communications, Phonograph, Vinyl, Record Scratch 08 SND13872.wav</ShortName>
					<CachePath>SFX/Communications, Phonograph, Vinyl, Record Scratch 08 SND13872_A8356449.wem</CachePath>
				</File>
				<File Id="77993868" Language="SFX" Streaming="false" Location="Memory">
					<ShortName>NewStems D54 Furious.wav</ShortName>
					<CachePath>SFX/NewStems D54 Furious_FBC78EF0.wem</CachePath>
				</File>
				<File Id="94231916" Language="SFX" Streaming="false" Location="Memory">
					<ShortName>EnemyHitFull.wav</ShortName>
					<CachePath>SFX/EnemyHitFull_E9170620.wem</CachePath>
				</File>
				<File Id="101762498" Language="SFX" Streaming="false" Location="Memory">
					<ShortName>IceBlockWooshes.wav</ShortName>
					<CachePath>SFX/IceBlockWooshes_F0C80020.wem</CachePath>
				</File>
				<File Id="108359842" Language="SFX" Streaming="false" Location="Memory">
					<ShortName>CrystalTones.wav</ShortName>
					<CachePath>SFX/CrystalTones_CD8180DC.wem</CachePath>
				</File>
				<File Id="119298661" Language="SFX" Streaming="false" Location="Memory">
					<ShortName>Objects, Misc, Paint, Spray Paint Can, Shake SND29085.wav</ShortName>
					<CachePath>SFX/Objects, Misc, Paint, Spray Paint Can, Shake SND29085_2B6C36E6.wem</CachePath>
				</File>
				<File Id="123022695" Language="SFX" Streaming="false" Location="Memory">
					<ShortName>PlayerHitImpact.wav</ShortName>
					<CachePath>SFX/PlayerHitImpact_0E4A869D.wem</CachePath>
				</File>
				<File Id="128351763" Language="SFX" Streaming="false" Location="Memory">
					<ShortName>Kick1.wav</ShortName>
					<CachePath>SFX/Kick1_818F3B66.wem</CachePath>
				</File>
				<File Id="135118416" Language="SFX" Streaming="false" Location="Memory">
					<ShortName>Objects, Misc, Spray Paint, Painting, Aerosol SND70613.wav</ShortName>
					<CachePath>SFX/Objects, Misc, Spray Paint, Painting, Aerosol SND70613_548B16BC.wem</CachePath>
				</File>
				<File Id="144065966" Language="SFX" Streaming="false" Location="Memory">
					<ShortName>CrystalTones.wav</ShortName>
					<CachePath>SFX/CrystalTones_10B9C241.wem</CachePath>
				</File>
				<File Id="152936960" Language="SFX" Streaming="false" Location="Memory">
					<ShortName>Objects, Misc, Paint, Spray Paint Can, Shake SND29085.wav</ShortName>
					<CachePath>SFX/Objects, Misc, Paint, Spray Paint Can, Shake SND29085_EAF5D6F7.wem</CachePath>
				</File>
				<File Id="162829338" Language="SFX" Streaming="false" Location="Memory">
					<ShortName>CrystalTones.wav</ShortName>
					<CachePath>SFX/CrystalTones_DA56C6CA.wem</CachePath>
				</File>
				<File Id="167927468" Language="SFX" Streaming="false" Location="Memory">
					<ShortName>Objects, Misc, Paint, Spray Paint Can, Shake SND29085.wav</ShortName>
					<CachePath>SFX/Objects, Misc, Paint, Spray Paint Can, Shake SND29085_52477903.wem</CachePath>
				</File>
				<File Id="178823695" Language="SFX" Streaming="false" Location="Memory">
					<ShortName>Fire3.wav</ShortName>
					<CachePath>SFX/Fire3_818F3B66.wem</CachePath>
				</File>
				<File Id="188725556" Language="SFX" Streaming="false" Location="Memory">
					<ShortName>Communications, Phonograph, Vinyl, Record Scratch 14 SND13866.wav</ShortName>
					<CachePath>SFX/Communications, Phonograph, Vinyl, Record Scratch 14 SND13866_ADC10A19.wem</CachePath>
				</File>
				<File Id="190951527" Language="SFX" Streaming="false" Location="Memory">
					<ShortName>NewStems 23-808 Aristocrat Kit.wav</ShortName>
					<CachePath>SFX/NewStems 23-808 Aristocrat Kit_FBC78EF0.wem</CachePath>
				</File>
				<File Id="200077581" Language="SFX" Streaming="false" Location="Memory">
					<ShortName>Objects, Misc, Paint, Spray Can, Marble, Shake SND30684.wav</ShortName>
					<CachePath>SFX/Objects, Misc, Paint, Spray Can, Marble, Shake SND30684_9588A38E.wem</CachePath>
				</File>
				<File Id="220814183" Language="SFX" Streaming="false" Location="Memory">
					<ShortName>PlayerHitDowner.wav</ShortName>
					<CachePath>SFX/PlayerHitDowner_ACD55C21.wem</CachePath>
				</File>
				<File Id="242173308" Language="SFX" Streaming="false" Location="Memory">
					<ShortName>Underground50S3.wav</ShortName>
					<CachePath>SFX/Underground50S3_FBC78EF0.wem</CachePath>
				</File>
				<File Id="256974757" Language="SFX" Streaming="false" Location="Memory">
					<ShortName>Objects, Misc, Spray Paint, Painting, Aerosol SND70613.wav</ShortName>
					<CachePath>SFX/Objects, Misc, Spray Paint, Painting, Aerosol SND70613_A844FEFE.wem</CachePath>
				</File>
				<File Id="320125018" Language="SFX" Streaming="false" Location="Memory">
					<ShortName>IceBlockWooshes.wav</ShortName>
					<CachePath>SFX/IceBlockWooshes_907CAAA9.wem</CachePath>
				</File>
				<File Id="355475302" Language="SFX" Streaming="false" Location="Memory">
					<ShortName>Objects, Misc, Spray Paint, Painting, Aerosol SND70613.wav</ShortName>
					<CachePath>SFX/Objects, Misc, Spray Paint, Painting, Aerosol SND70613_08A40089.wem</CachePath>
				</File>
				<File Id="361976253" Language="SFX" Streaming="false" Location="Memory">
					<ShortName>EnemyHitFull.wav</ShortName>
					<CachePath>SFX/EnemyHitFull_BA5A28CF.wem</CachePath>
				</File>
				<File Id="362380582" Language="SFX" Streaming="false" Location="Memory">
					<ShortName>Swoosh1.wav</ShortName>
					<CachePath>SFX/Swoosh1_818F3B66.wem</CachePath>
				</File>
				<File Id="397062548" Language="SFX" Streaming="false" Location="Memory">
					<ShortName>Shimmer1.wav</ShortName>
					<CachePath>SFX/Shimmer1_818F3B66.wem</CachePath>
				</File>
				<File Id="403578445" Language="SFX" Streaming="false" Location="Memory">
					<ShortName>PlayerHitDowner.wav</ShortName>
					<CachePath>SFX/PlayerHitDowner_1F047EF7.wem</CachePath>
				</File>
				<File Id="404034492" Language="SFX" Streaming="false" Location="Memory">
					<ShortName>SmolScratch.wav</ShortName>
					<CachePath>SFX/SmolScratch_DC99C211.wem</CachePath>
				</File>
				<File Id="456996073" Language="SFX" Streaming="false" Location="Memory">
					<ShortName>Dashing.wav</ShortName>
					<CachePath>SFX/Dashing_D8DE3F02.wem</CachePath>
				</File>
				<File Id="469236046" Language="SFX" Streaming="false" Location="Memory">
					<ShortName>Ice3.wav</ShortName>
					<CachePath>SFX/Ice3_818F3B66.wem</CachePath>
				</File>
				<File Id="470829322" Language="SFX" Streaming="false" Location="Memory">
					<ShortName>EnemyHitFull.wav</ShortName>
					<CachePath>SFX/EnemyHitFull_73616B20.wem</CachePath>
				</File>
				<File Id="497414986" Language="SFX" Streaming="false" Location="Memory">
					<ShortName>CrystalZap.wav</ShortName>
					<CachePath>SFX/CrystalZap_818F3B66.wem</CachePath>
				</File>
				<File Id="510362844" Language="SFX" Streaming="false" Location="Memory">
					<ShortName>Objects, Misc, Paint, Spray Paint Can, Shake SND29085.wav</ShortName>
					<CachePath>SFX/Objects, Misc, Paint, Spray Paint Can, Shake SND29085_3835B1E5.wem</CachePath>
				</File>
				<File Id="522681793" Language="SFX" Streaming="false" Location="Memory">
					<ShortName>NewStems Taiko.wav</ShortName>
					<CachePath>SFX/NewStems Taiko_FBC78EF0.wem</CachePath>
				</File>
				<File Id="524500419" Language="SFX" Streaming="false" Location="Memory">
					<ShortName>PlayerHitDowner.wav</ShortName>
					<CachePath>SFX/PlayerHitDowner_094C70E3.wem</CachePath>
				</File>
				<File Id="535223205" Language="SFX" Streaming="false" Location="Memory">
					<ShortName>MicTap3.wav</ShortName>
					<CachePath>SFX/MicTap3_818F3B66.wem</CachePath>
				</File>
				<File Id="546120684" Language="SFX" Streaming="false" Location="Memory">
					<ShortName>CrowdSurfLoop.wav</ShortName>
					<CachePath>SFX/CrowdSurfLoop_11A93380.wem</CachePath>
				</File>
				<File Id="560172071" Language="SFX" Streaming="false" Location="Memory">
					<ShortName>EnemyHitFull.wav</ShortName>
					<CachePath>SFX/EnemyHitFull_651E6C52.wem</CachePath>
				</File>
				<File Id="567844658" Language="SFX" Streaming="false" Location="Memory">
					<ShortName>Lever2.wav</ShortName>
					<CachePath>SFX/Lever2_818F3B66.wem</CachePath>
				</File>
				<File Id="583637567" Language="SFX" Streaming="false" Location="Memory">
					<ShortName>EnemyHitFull.wav</ShortName>
					<CachePath>SFX/EnemyHitFull_2D5FA1F8.wem</CachePath>
				</File>
				<File Id="595136245" Language="SFX" Streaming="false" Location="Memory">
					<ShortName>RockPlatformPush2.wav</ShortName>
					<CachePath>SFX/RockPlatformPush2_DA4B44F3.wem</CachePath>
				</File>
				<File Id="596267822" Language="SFX" Streaming="false" Location="Memory">
					<ShortName>EnemyHitFull.wav</ShortName>
					<CachePath>SFX/EnemyHitFull_8DF2FD27.wem</CachePath>
				</File>
				<File Id="618127826" Language="SFX" Streaming="false" Location="Memory">
					<ShortName>IceBlockWooshes.wav</ShortName>
					<CachePath>SFX/IceBlockWooshes_40878711.wem</CachePath>
				</File>
				<File Id="624941402" Language="SFX" Streaming="false" Location="Memory">
					<ShortName>SmollScratch.wav</ShortName>
					<CachePath>SFX/SmollScratch_926E4C94.wem</CachePath>
				</File>
				<File Id="630432816" Language="SFX" Streaming="false" Location="Memory">
					<ShortName>Lever1.wav</ShortName>
					<CachePath>SFX/Lever1_818F3B66.wem</CachePath>
				</File>
				<File Id="639389320" Language="SFX" Streaming="false" Location="Memory">
					<ShortName>PlayerHitImpact.wav</ShortName>
					<CachePath>SFX/PlayerHitImpact_E134E976.wem</CachePath>
				</File>
				<File Id="647426739" Language="SFX" Streaming="false" Location="Memory">
					<ShortName>Communications, Phonograph, Vinyl, Record Scratch 04 SND13876 1.wav</ShortName>
					<CachePath>SFX/Communications, Phonograph, Vinyl, Record Scratch 04 SND13876 1_06D5701A.wem</CachePath>
				</File>
				<File Id="648565713" Language="SFX" Streaming="false" Location="Memory">
					<ShortName>NewStems OrchestralBell.wav</ShortName>
					<CachePath>SFX/NewStems OrchestralBell_FBC78EF0.wem</CachePath>
				</File>
				<File Id="654079656" Language="SFX" Streaming="false" Location="Memory">
					<ShortName>Fire1.wav</ShortName>
					<CachePath>SFX/Fire1_818F3B66.wem</CachePath>
				</File>
				<File Id="654308591" Language="SFX" Streaming="false" Location="Memory">
					<ShortName>PlayerHitDowner.wav</ShortName>
					<CachePath>SFX/PlayerHitDowner_87535765.wem</CachePath>
				</File>
				<File Id="660611193" Language="SFX" Streaming="false" Location="Memory">
					<ShortName>CrystalTones.wav</ShortName>
					<CachePath>SFX/CrystalTones_DBA94521.wem</CachePath>
				</File>
				<File Id="664797136" Language="SFX" Streaming="false" Location="Memory">
					<ShortName>Shimmer2.wav</ShortName>
					<CachePath>SFX/Shimmer2_818F3B66.wem</CachePath>
				</File>
				<File Id="669664009" Language="SFX" Streaming="false" Location="Memory">
					<ShortName>Kick2.wav</ShortName>
					<CachePath>SFX/Kick2_818F3B66.wem</CachePath>
				</File>
				<File Id="672424488" Language="SFX" Streaming="false" Location="Memory">
					<ShortName>Objects, Misc, Paint, Spray Can, Marble, Shake SND30684.wav</ShortName>
					<CachePath>SFX/Objects, Misc, Paint, Spray Can, Marble, Shake SND30684_D7907CD1.wem</CachePath>
				</File>
				<File Id="680414174" Language="SFX" Streaming="false" Location="Memory">
					<ShortName>Communications, Phonograph, Transition, Scratch, Rewind, Vinyl 01 SND61199.wav</ShortName>
					<CachePath>SFX/Communications, Phonograph, Transition, Scratch, Rewind, Vinyl 01 SND61199_D8426847.wem</CachePath>
				</File>
				<File Id="682767542" Language="SFX" Streaming="false" Location="Memory">
					<ShortName>Objects, Misc, Spray Paint, Painting, Aerosol SND70613.wav</ShortName>
					<CachePath>SFX/Objects, Misc, Spray Paint, Painting, Aerosol SND70613_96A6D7B5.wem</CachePath>
				</File>
				<File Id="695187573" Language="SFX" Streaming="false" Location="Memory">
					<ShortName>PlayerHitImpact.wav</ShortName>
					<CachePath>SFX/PlayerHitImpact_D05A1D10.wem</CachePath>
				</File>
				<File Id="700571979" Language="SFX" Streaming="false" Location="Memory">
					<ShortName>PlayerHitDowner.wav</ShortName>
					<CachePath>SFX/PlayerHitDowner_08DB20D2.wem</CachePath>
				</File>
				<File Id="706702062" Language="SFX" Streaming="false" Location="Memory">
					<ShortName>CrystalShimmers.wav</ShortName>
					<CachePath>SFX/CrystalShimmers_C3225900.wem</CachePath>
				</File>
				<File Id="733335054" Language="SFX" Streaming="false" Location="Memory">
					<ShortName>IceBlockWooshes.wav</ShortName>
					<CachePath>SFX/IceBlockWooshes_861873C6.wem</CachePath>
				</File>
				<File Id="742707364" Language="SFX" Streaming="false" Location="Memory">
					<ShortName>PlayerHitDowner.wav</ShortName>
					<CachePath>SFX/PlayerHitDowner_018C8FF8.wem</CachePath>
				</File>
				<File Id="766739187" Language="SFX" Streaming="false" Location="Memory">
					<ShortName>PlayRecordScratch.wav</ShortName>
					<CachePath>SFX/PlayRecordScratch_B6E802AC.wem</CachePath>
				</File>
				<File Id="771010357" Language="SFX" Streaming="false" Location="Memory">
					<ShortName>IceBlockWooshes.wav</ShortName>
					<CachePath>SFX/IceBlockWooshes_A9FE4798.wem</CachePath>
				</File>
				<File Id="771789552" Language="SFX" Streaming="false" Location="Memory">
					<ShortName>NewStems 7-Kontakt 7.wav</ShortName>
					<CachePath>SFX/NewStems 7-Kontakt 7_FBC78EF0.wem</CachePath>
				</File>
				<File Id="799885752" Language="SFX" Streaming="false" Location="Memory">
					<ShortName>NewStems 10-Chants &amp; Stabs Kit.wav</ShortName>
					<CachePath>SFX/NewStems 10-Chants &amp; Stabs Kit_FBC78EF0.wem</CachePath>
				</File>
				<File Id="824108392" Language="SFX" Streaming="false" Location="Memory">
					<ShortName>Ice2.wav</ShortName>
					<CachePath>SFX/Ice2_818F3B66.wem</CachePath>
				</File>
				<File Id="834049591" Language="SFX" Streaming="false" Location="Memory">
					<ShortName>NewStems AllInTheGame.wav</ShortName>
					<CachePath>SFX/NewStems AllInTheGame_FBC78EF0.wem</CachePath>
				</File>
				<File Id="853954014" Language="SFX" Streaming="false" Location="Memory">
					<ShortName>CrystalShimmers.wav</ShortName>
					<CachePath>SFX/CrystalShimmers_9DF8CA20.wem</CachePath>
				</File>
				<File Id="859013703" Language="SFX" Streaming="false" Location="Memory">
					<ShortName>Communications, Phonograph, Vinyl, Record Scratch 09 SND13871.wav</ShortName>
					<CachePath>SFX/Communications, Phonograph, Vinyl, Record Scratch 09 SND13871_BC92987B.wem</CachePath>
				</File>
				<File Id="860878555" Language="SFX" Streaming="false" Location="Memory">
					<ShortName>Dashing.wav</ShortName>
					<CachePath>SFX/Dashing_446DB767.wem</CachePath>
				</File>
				<File Id="870905338" Language="SFX" Streaming="false" Location="Memory">
					<ShortName>LotsOfSmallScratch.wav</ShortName>
					<CachePath>SFX/LotsOfSmallScratch_977BC18E.wem</CachePath>
				</File>
				<File Id="891929607" Language="SFX" Streaming="false" Location="Memory">
					<ShortName>LotsOfSmallScratch.wav</ShortName>
					<CachePath>SFX/LotsOfSmallScratch_01325435.wem</CachePath>
				</File>
				<File Id="896693686" Language="SFX" Streaming="false" Location="Memory">
					<ShortName>EnemyHitFull.wav</ShortName>
					<CachePath>SFX/EnemyHitFull_3CE83CA9.wem</CachePath>
				</File>
				<File Id="896701260" Language="SFX" Streaming="false" Location="Memory">
					<ShortName>Objects, Misc, Spray Paint, Painting, Aerosol SND70613.wav</ShortName>
					<CachePath>SFX/Objects, Misc, Spray Paint, Painting, Aerosol SND70613_35360599.wem</CachePath>
				</File>
				<File Id="904304785" Language="SFX" Streaming="false" Location="Memory">
					<ShortName>Objects, Misc, Spray Paint, Painting, Aerosol SND70613.wav</ShortName>
					<CachePath>SFX/Objects, Misc, Spray Paint, Painting, Aerosol SND70613_B02E92DE.wem</CachePath>
				</File>
				<File Id="908953981" Language="SFX" Streaming="false" Location="Memory">
					<ShortName>PlayerHitImpact.wav</ShortName>
					<CachePath>SFX/PlayerHitImpact_1BB0DF92.wem</CachePath>
				</File>
				<File Id="909458974" Language="SFX" Streaming="false" Location="Memory">
					<ShortName>Zap1.wav</ShortName>
					<CachePath>SFX/Zap1_818F3B66.wem</CachePath>
				</File>
				<File Id="929853616" Language="SFX" Streaming="false" Location="Memory">
					<ShortName>Fire2.wav</ShortName>
					<CachePath>SFX/Fire2_818F3B66.wem</CachePath>
				</File>
				<File Id="930362323" Language="SFX" Streaming="false" Location="Memory">
					<ShortName>PlayerHitImpact.wav</ShortName>
					<CachePath>SFX/PlayerHitImpact_3BD96E54.wem</CachePath>
				</File>
				<File Id="930947941" Language="SFX" Streaming="false" Location="Memory">
					<ShortName>Ice1.wav</ShortName>
					<CachePath>SFX/Ice1_818F3B66.wem</CachePath>
				</File>
				<File Id="935653253" Language="SFX" Streaming="false" Location="Memory">
					<ShortName>EnemyHitFull.wav</ShortName>
					<CachePath>SFX/EnemyHitFull_4396A49F.wem</CachePath>
				</File>
				<File Id="953151695" Language="SFX" Streaming="false" Location="Memory">
					<ShortName>PlayerHitDowner.wav</ShortName>
					<CachePath>SFX/PlayerHitDowner_45B24C9B.wem</CachePath>
				</File>
				<File Id="956823132" Language="SFX" Streaming="false" Location="Memory">
					<ShortName>IceBlockWooshes.wav</ShortName>
					<CachePath>SFX/IceBlockWooshes_1AE3F1DC.wem</CachePath>
				</File>
				<File Id="989052792" Language="SFX" Streaming="false" Location="Memory">
					<ShortName>SmallScratch.wav</ShortName>
					<CachePath>SFX/SmallScratch_91CA9725.wem</CachePath>
				</File>
				<File Id="1025029307" Language="SFX" Streaming="false" Location="Memory">
					<ShortName>Dashing.wav</ShortName>
					<CachePath>SFX/Dashing_97361679.wem</CachePath>
				</File>
				<File Id="1027865135" Language="SFX" Streaming="false" Location="Memory">
					<ShortName>PlayerHitImpact.wav</ShortName>
					<CachePath>SFX/PlayerHitImpact_2A452683.wem</CachePath>
				</File>
				<File Id="1028609631" Language="SFX" Streaming="false" Location="Memory">
					<ShortName>PlayerHitImpact.wav</ShortName>
					<CachePath>SFX/PlayerHitImpact_90667E1B.wem</CachePath>
				</File>
				<File Id="1032575052" Language="SFX" Streaming="false" Location="Memory">
					<ShortName>IceBlockWooshes.wav</ShortName>
					<CachePath>SFX/IceBlockWooshes_BA941C4D.wem</CachePath>
				</File>
			</Media>
			<Plugins>
				<ShareSets>
					<Plugin Id="1008402193" Name="Low_Pass_20KHz" LibName="Wwise Parametric EQ" LibId="6881283"/>
				</ShareSets>
			</Plugins>
			<Events>
				<Event Id="3035572085" Name="ButtonHover" DurationType="OneShot" DurationMin="0.14352083" DurationMax="0.36171988">
					<MediaRefs>
						<MediaRef Id="20835932"/>
						<MediaRef Id="404034492"/>
						<MediaRef Id="624941402"/>
						<MediaRef Id="870905338"/>
						<MediaRef Id="891929607"/>
						<MediaRef Id="989052792"/>
					</MediaRefs>
				</Event>
				<Event Id="317641954" Name="ButtonPress" DurationType="OneShot" DurationMin="0.41620064" DurationMax="0.8878672">
					<MediaRefs>
						<MediaRef Id="73496553"/>
						<MediaRef Id="188725556"/>
						<MediaRef Id="647426739"/>
						<MediaRef Id="859013703"/>
					</MediaRefs>
				</Event>
				<Event Id="1739654744" Name="CrowdSurf" DurationType="Infinite">
					<MediaRefs>
						<MediaRef Id="546120684"/>
					</MediaRefs>
					<ActionSetState>
						<ActionSetStateEntry GroupId="2352559104" Id="2260458779" Name="InCrowdSurf"/>
					</ActionSetState>
				</Event>
				<Event Id="3444057113" Name="Crystal" DurationType="OneShot" DurationMin="3.4768662" DurationMax="4.176854">
					<MediaRefs>
						<MediaRef Id="108359842"/>
						<MediaRef Id="144065966"/>
						<MediaRef Id="162829338"/>
						<MediaRef Id="497414986"/>
						<MediaRef Id="660611193"/>
						<MediaRef Id="706702062"/>
						<MediaRef Id="853954014"/>
					</MediaRefs>
				</Event>
				<Event Id="418751485" Name="IceBlock" DurationType="OneShot" DurationMin="1.7034016" DurationMax="2.37977">
					<MediaRefs>
						<MediaRef Id="101762498"/>
						<MediaRef Id="320125018"/>
						<MediaRef Id="618127826"/>
						<MediaRef Id="733335054"/>
						<MediaRef Id="771010357"/>
						<MediaRef Id="956823132"/>
						<MediaRef Id="1032575052"/>
					</MediaRefs>
				</Event>
				<Event Id="2782712987" Name="Lever" DurationType="OneShot" DurationMin="2.4" DurationMax="2.4">
					<MediaRefs>
						<MediaRef Id="567844658"/>
						<MediaRef Id="630432816"/>
					</MediaRefs>
				</Event>
				<Event Id="2689877988" Name="LightningMusicLoop" DurationType="OneShot" DurationMin="38.4" DurationMax="38.4">
					<MediaRefs>
						<MediaRef Id="77993868"/>
						<MediaRef Id="190951527"/>
						<MediaRef Id="522681793"/>
						<MediaRef Id="648565713"/>
						<MediaRef Id="771789552"/>
						<MediaRef Id="799885752"/>
						<MediaRef Id="834049591"/>
					</MediaRefs>
				</Event>
				<Event Id="2248677623" Name="MeleeFire" DurationType="OneShot" DurationMin="0.6250113" DurationMax="0.6250113">
					<MediaRefs>
						<MediaRef Id="28928322"/>
						<MediaRef Id="55840581"/>
						<MediaRef Id="59239616"/>
						<MediaRef Id="128351763"/>
						<MediaRef Id="178823695"/>
						<MediaRef Id="535223205"/>
						<MediaRef Id="654079656"/>
						<MediaRef Id="669664009"/>
						<MediaRef Id="929853616"/>
					</MediaRefs>
				</Event>
				<Event Id="1651067412" Name="MeleeIce" DurationType="OneShot" DurationMin="0.5" DurationMax="0.5">
					<MediaRefs>
						<MediaRef Id="28928322"/>
						<MediaRef Id="55840581"/>
						<MediaRef Id="59239616"/>
						<MediaRef Id="128351763"/>
						<MediaRef Id="469236046"/>
						<MediaRef Id="535223205"/>
						<MediaRef Id="669664009"/>
						<MediaRef Id="824108392"/>
						<MediaRef Id="930947941"/>
					</MediaRefs>
				</Event>
				<Event Id="1583612915" Name="MeleeLightning" DurationType="OneShot" DurationMin="0.6250113" DurationMax="0.75">
					<MediaRefs>
						<MediaRef Id="5318352"/>
						<MediaRef Id="28928322"/>
						<MediaRef Id="55840581"/>
						<MediaRef Id="59239616"/>
						<MediaRef Id="128351763"/>
						<MediaRef Id="535223205"/>
						<MediaRef Id="669664009"/>
						<MediaRef Id="909458974"/>
					</MediaRefs>
				</Event>
				<Event Id="3991942870" Name="Music" DurationType="Infinite">
					<ActionSetState>
						<ActionSetStateEntry GroupId="1021618141" Id="89505537" Name="Gameplay"/>
					</ActionSetState>
				</Event>
				<Event Id="1843531235" Name="PlayButton" DurationType="OneShot" DurationMin="1.1446644" DurationMax="2.1689167">
					<MediaRefs>
						<MediaRef Id="680414174"/>
						<MediaRef Id="766739187"/>
					</MediaRefs>
				</Event>
				<Event Id="2525052962" Name="PlayerDash" DurationType="OneShot" DurationMin="0.2684375" DurationMax="2.8776808">
					<MediaRefs>
						<MediaRef Id="8926796"/>
						<MediaRef Id="456996073"/>
						<MediaRef Id="860878555"/>
						<MediaRef Id="1025029307"/>
					</MediaRefs>
				</Event>
				<Event Id="3537581393" Name="PlayerHurt" DurationType="OneShot" DurationMin="1.8891193" DurationMax="2.3589551">
					<MediaRefs>
						<MediaRef Id="123022695"/>
						<MediaRef Id="220814183"/>
						<MediaRef Id="403578445"/>
						<MediaRef Id="524500419"/>
						<MediaRef Id="639389320"/>
						<MediaRef Id="654308591"/>
						<MediaRef Id="695187573"/>
						<MediaRef Id="700571979"/>
						<MediaRef Id="742707364"/>
						<MediaRef Id="908953981"/>
						<MediaRef Id="930362323"/>
						<MediaRef Id="953151695"/>
						<MediaRef Id="1027865135"/>
						<MediaRef Id="1028609631"/>
					</MediaRefs>
					<PluginRefs>
						<ShareSets>
							<PluginRef Id="1008402193"/>
						</ShareSets>
					</PluginRefs>
				</Event>
				<Event Id="1744863420" Name="RangedFire" DurationType="OneShot" DurationMin="0.6250113" DurationMax="0.6250113">
					<MediaRefs>
						<MediaRef Id="43950693"/>
						<MediaRef Id="178823695"/>
						<MediaRef Id="362380582"/>
						<MediaRef Id="397062548"/>
						<MediaRef Id="654079656"/>
						<MediaRef Id="664797136"/>
						<MediaRef Id="929853616"/>
					</MediaRefs>
				</Event>
				<Event Id="2982846157" Name="RangedIce" DurationType="OneShot" DurationMin="0.6250113" DurationMax="0.6250113">
					<MediaRefs>
						<MediaRef Id="43950693"/>
						<MediaRef Id="362380582"/>
						<MediaRef Id="397062548"/>
						<MediaRef Id="469236046"/>
						<MediaRef Id="664797136"/>
						<MediaRef Id="824108392"/>
						<MediaRef Id="930947941"/>
					</MediaRefs>
				</Event>
				<Event Id="1899629126" Name="RangedLightning" DurationType="OneShot" DurationMin="0.6250113" DurationMax="0.75">
					<MediaRefs>
						<MediaRef Id="5318352"/>
						<MediaRef Id="43950693"/>
						<MediaRef Id="362380582"/>
						<MediaRef Id="397062548"/>
						<MediaRef Id="664797136"/>
						<MediaRef Id="909458974"/>
					</MediaRefs>
				</Event>
				<Event Id="1518733879" Name="RockPlatformPuzzle" DurationType="OneShot" DurationMin="1.5425884" DurationMax="1.9724116">
					<MediaRefs>
						<MediaRef Id="64644625"/>
						<MediaRef Id="595136245"/>
					</MediaRefs>
				</Event>
				<Event Id="427386941" Name="RoomMus" DurationType="Infinite">
					<MediaRefs>
						<MediaRef Id="242173308"/>
					</MediaRefs>
				</Event>
				<Event Id="2460311919" Name="SkeletonHit" DurationType="OneShot" DurationMin="0.86824834" DurationMax="1.3890802">
					<MediaRefs>
						<MediaRef Id="94231916"/>
						<MediaRef Id="361976253"/>
						<MediaRef Id="470829322"/>
						<MediaRef Id="560172071"/>
						<MediaRef Id="583637567"/>
						<MediaRef Id="596267822"/>
						<MediaRef Id="896693686"/>
						<MediaRef Id="935653253"/>
					</MediaRefs>
				</Event>
				<Event Id="3290622745" Name="WordPickup" DurationType="OneShot" DurationMin="0.799734" DurationMax="1.018271">
					<MediaRefs>
						<MediaRef Id="3886522"/>
						<MediaRef Id="21833884"/>
						<MediaRef Id="42034528"/>
						<MediaRef Id="119298661"/>
						<MediaRef Id="135118416"/>
						<MediaRef Id="152936960"/>
						<MediaRef Id="167927468"/>
						<MediaRef Id="200077581"/>
						<MediaRef Id="256974757"/>
						<MediaRef Id="355475302"/>
						<MediaRef Id="510362844"/>
						<MediaRef Id="672424488"/>
						<MediaRef Id="682767542"/>
						<MediaRef Id="896701260"/>
						<MediaRef Id="904304785"/>
					</MediaRefs>
				</Event>
			</Events>
			<StateGroups>
				<StateGroup Id="1021618141" Name="MusicState">
					<States>
						<State Id="89505537" Name="Gameplay"/>
						<State Id="748895195" Name="None"/>
					</States>
				</StateGroup>
				<StateGroup Id="2352559104" Name="CrowdSurfing">
					<States>
						<State Id="748895195" Name="None"/>
						<State Id="2260458779" Name="InCrowdSurf"/>
						<State Id="2475500331" Name="OutOfCrowdSurf"/>
					</States>
				</StateGroup>
			</StateGroups>
		</SoundBank>
	</SoundBanks>
	<FileHash>{C732565D-6BC8-FF28-A901-FE6BCB8EB9EE}</FileHash>
</SoundBanksInfo>
